matter_exceptions/__about__.py
matter_exceptions/__init__.py
matter_exceptions/base_api_exception.py
matter_exceptions/base_fastapi_exception.py
matter_exceptions/detailed_exception.py
matter_exceptions/utils.py
matter_exceptions/exceptions/api.py
matter_exceptions/exceptions/fastapi.py
matter_exceptions/exceptions/general.py
matter_exceptions-2.0.0.dist-info/METADATA
matter_exceptions-2.0.0.dist-info/WHEEL
matter_exceptions-2.0.0.dist-info/licenses/LICENSE.txt
matter_exceptions-2.0.0.dist-info/RECORD
