Metadata-Version: 2.1
Name: matter-exceptions
Version: 2.0.0
Project-URL: Documentation, https://github.com/Matter/matter-exceptions#readme
Project-URL: Issues, https://github.com/Matter/matter-exceptions/issues
Project-URL: Source, https://github.com/Matter/matter-exceptions
Author-email: Rômulo Jales <romulo@thisismatter.com>
License-Expression: MIT
License-File: LICENSE.txt
Classifier: Development Status :: 4 - Beta
Classifier: Programming Language :: Python
Classifier: Programming Language :: Python :: 3.10
Classifier: Programming Language :: Python :: 3.11
Classifier: Programming Language :: Python :: Implementation :: CPython
Classifier: Programming Language :: Python :: Implementation :: PyPy
Requires-Python: >=3.10
Provides-Extra: fastapi
Requires-Dist: fastapi>=0.88.0; extra == 'fastapi'
Provides-Extra: sentry
Requires-Dist: sentry-sdk>=1.23.1; extra == 'sentry'
